{"tree":{"text":"scheduler","children":[{"text":"examples","children":[{"text":"proc1-c1-fcfs.out","icon":"fa fa-file"},{"text":"proc1-c1-pri.out","icon":"fa fa-file"},{"text":"proc1-c1-psjf.out","icon":"fa fa-file"},{"text":"proc1-c1-rr1.out","icon":"fa fa-file"},{"text":"proc1-c1-rr2.out","icon":"fa fa-file"},{"text":"proc1-c1-rr4.out","icon":"fa fa-file"},{"text":"proc1-c2-fcfs.out","icon":"fa fa-file"},{"text":"proc1-c2-pri.out","icon":"fa fa-file"},{"text":"proc1-c2-psjf.out","icon":"fa fa-file"},{"text":"proc1-c2-rr1.out","icon":"fa fa-file"},{"text":"proc1-c2-rr2.out","icon":"fa fa-file"},{"text":"proc1-c2-rr4.out","icon":"fa fa-file"},{"text":"proc1.csv","icon":"fa fa-file"},{"text":"proc2-c1-fcfs.out","icon":"fa fa-file"},{"text":"proc2-c1-pri.out","icon":"fa fa-file"},{"text":"proc2-c1-psjf.out","icon":"fa fa-file"},{"text":"proc2-c1-rr1.out","icon":"fa fa-file"},{"text":"proc2-c1-rr2.out","icon":"fa fa-file"},{"text":"proc2-c1-rr4.out","icon":"fa fa-file"},{"text":"proc2-c2-fcfs.out","icon":"fa fa-file"},{"text":"proc2-c2-pri.out","icon":"fa fa-file"},{"text":"proc2-c2-psjf.out","icon":"fa fa-file"},{"text":"proc2-c2-rr1.out","icon":"fa fa-file"},{"text":"proc2-c2-rr2.out","icon":"fa fa-file"},{"text":"proc2-c2-rr4.out","icon":"fa fa-file"},{"text":"proc2.csv","icon":"fa fa-file"},{"text":"proc3-c1-fcfs.out","icon":"fa fa-file"},{"text":"proc3-c1-pri.out","icon":"fa fa-file"},{"text":"proc3-c1-psjf.out","icon":"fa fa-file"},{"text":"proc3-c1-rr1.out","icon":"fa fa-file"},{"text":"proc3-c1-rr2.out","icon":"fa fa-file"},{"text":"proc3-c1-rr4.out","icon":"fa fa-file"},{"text":"proc3-c2-fcfs.out","icon":"fa fa-file"},{"text":"proc3-c2-pri.out","icon":"fa fa-file"},{"text":"proc3-c2-psjf.out","icon":"fa fa-file"},{"text":"proc3-c2-rr1.out","icon":"fa fa-file"},{"text":"proc3-c2-rr2.out","icon":"fa fa-file"},{"text":"proc3-c2-rr4.out","icon":"fa fa-file"},{"text":"proc3-c4-fcfs.out","icon":"fa fa-file"},{"text":"proc3-c4-pri.out","icon":"fa fa-file"},{"text":"proc3-c4-psjf.out","icon":"fa fa-file"},{"text":"proc3-c4-rr1.out","icon":"fa fa-file"},{"text":"proc3-c4-rr2.out","icon":"fa fa-file"},{"text":"proc3-c4-rr4.out","icon":"fa fa-file"},{"text":"proc3.csv","icon":"fa fa-file"}],"icon":"fa fa-folder"},{"text":"libpriqueue","children":[{"text":"libpriqueue.c","icon":"fa fa-file"},{"text":"libpriqueue.h","icon":"fa fa-file"}],"icon":"fa fa-folder"},{"text":"libscheduler","children":[{"text":"libscheduler.c","icon":"fa fa-file"},{"text":"libscheduler.h","icon":"fa fa-file"}],"icon":"fa fa-folder"},{"text":"Makefile","icon":"fa fa-file"},{"text":"examples.pl","icon":"fa fa-file"},{"text":"grade_report.html","icon":"fa fa-file"},{"text":"results.json","icon":"fa fa-file"},{"text":"simulator.c","icon":"fa fa-file"}],"icon":"fa fa-folder"},"commits":{"scheduler/libscheduler/libscheduler.c":[{"revision":84385,"author":"cliu81","date":"2016-04-29T02:03:25.258Z","msg":"w .00000001","action":"M"},{"revision":83280,"author":"cliu81","date":"2016-04-27T13:55:50.507Z","msg":"sch .00000000001","action":"M"},{"revision":83279,"author":"cliu81","date":"2016-04-27T13:54:25.001Z","msg":"sch .00000000001","action":"M"},{"revision":83278,"author":"cliu81","date":"2016-04-27T13:52:22.975Z","msg":"sch .00000000001","action":"M"},{"revision":82962,"author":"cliu81","date":"2016-04-27T02:40:40.182Z","msg":"sch .00000000001","action":"M"},{"revision":82960,"author":"cliu81","date":"2016-04-27T02:37:19.743Z","msg":"sch .00000000001","action":"M"},{"revision":82941,"author":"cliu81","date":"2016-04-27T02:16:34.787Z","msg":"sch .00000000001","action":"M"},{"revision":82905,"author":"cliu81","date":"2016-04-27T01:39:02.799Z","msg":"sch .00000000001","action":"M"},{"revision":82902,"author":"cliu81","date":"2016-04-27T01:35:40.046Z","msg":"sch .00000000001","action":"M"},{"revision":82898,"author":"cliu81","date":"2016-04-27T01:29:44.160Z","msg":"sch .00000000001","action":"M"},{"revision":82785,"author":"cliu81","date":"2016-04-26T14:11:30.518Z","msg":"sch .00000000001","action":"M"},{"revision":82753,"author":"cliu81","date":"2016-04-26T06:28:59.095Z","msg":"sch .00000000001","action":"M"},{"revision":78852,"author":"kocheva2","date":"2016-04-21T08:36:57.898Z","msg":"(No commit Message)","action":"A"}],"scheduler/results.json":[{"revision":84373,"author":"emsauer2","date":"2016-04-28T23:03:13.234Z","msg":"(No commit Message)","action":"M"},{"revision":84368,"author":"emsauer2","date":"2016-04-28T22:03:32.081Z","msg":"(No commit Message)","action":"M"},{"revision":83264,"author":"emsauer2","date":"2016-04-27T10:03:27.303Z","msg":"(No commit Message)","action":"M"},{"revision":82864,"author":"emsauer2","date":"2016-04-27T00:03:27.055Z","msg":"(No commit Message)","action":"M"},{"revision":82781,"author":"emsauer2","date":"2016-04-26T10:03:35.976Z","msg":"(No commit Message)","action":"M"},{"revision":80341,"author":"emsauer2","date":"2016-04-25T10:03:27.882Z","msg":"(No commit Message)","action":"M"},{"revision":79591,"author":"emsauer2","date":"2016-04-24T17:45:00.963Z","msg":"(No commit Message)","action":"M"},{"revision":79575,"author":"emsauer2","date":"2016-04-24T10:06:54.989Z","msg":"(No commit Message)","action":"A"}],"scheduler/libscheduler/libscheduler.h":[{"revision":82785,"author":"cliu81","date":"2016-04-26T14:11:30.518Z","msg":"sch .00000000001","action":"M"},{"revision":82753,"author":"cliu81","date":"2016-04-26T06:28:59.095Z","msg":"sch .00000000001","action":"M"},{"revision":78852,"author":"kocheva2","date":"2016-04-21T08:36:57.898Z","msg":"(No commit Message)","action":"A"}],"scheduler/grade_report.html":[{"revision":79575,"author":"emsauer2","date":"2016-04-24T10:06:54.989Z","msg":"(No commit Message)","action":"A"}],"scheduler":[{"revision":78852,"author":"kocheva2","date":"2016-04-21T08:36:57.898Z","msg":"(No commit Message)","action":"A"}],"scheduler/Makefile":[{"revision":78852,"author":"kocheva2","date":"2016-04-21T08:36:57.898Z","msg":"(No commit Message)","action":"A"}],"scheduler/examples":[{"revision":78852,"author":"kocheva2","date":"2016-04-21T08:36:57.898Z","msg":"(No commit Message)","action":"A"}],"scheduler/examples/proc1-c1-fcfs.out":[{"revision":78852,"author":"kocheva2","date":"2016-04-21T08:36:57.898Z","msg":"(No commit Message)","action":"A"}],"scheduler/examples/proc1-c1-pri.out":[{"revision":78852,"author":"kocheva2","date":"2016-04-21T08:36:57.898Z","msg":"(No commit Message)","action":"A"}],"scheduler/examples/proc1-c1-psjf.out":[{"revision":78852,"author":"kocheva2","date":"2016-04-21T08:36:57.898Z","msg":"(No commit Message)","action":"A"}],"scheduler/examples/proc1-c1-rr1.out":[{"revision":78852,"author":"kocheva2","date":"2016-04-21T08:36:57.898Z","msg":"(No commit Message)","action":"A"}],"scheduler/examples/proc1-c1-rr2.out":[{"revision":78852,"author":"kocheva2","date":"2016-04-21T08:36:57.898Z","msg":"(No commit Message)","action":"A"}],"scheduler/examples/proc1-c1-rr4.out":[{"revision":78852,"author":"kocheva2","date":"2016-04-21T08:36:57.898Z","msg":"(No commit Message)","action":"A"}],"scheduler/examples/proc1-c2-fcfs.out":[{"revision":78852,"author":"kocheva2","date":"2016-04-21T08:36:57.898Z","msg":"(No commit Message)","action":"A"}],"scheduler/examples/proc1-c2-pri.out":[{"revision":78852,"author":"kocheva2","date":"2016-04-21T08:36:57.898Z","msg":"(No commit Message)","action":"A"}],"scheduler/examples/proc1-c2-psjf.out":[{"revision":78852,"author":"kocheva2","date":"2016-04-21T08:36:57.898Z","msg":"(No commit Message)","action":"A"}],"scheduler/examples/proc1-c2-rr1.out":[{"revision":78852,"author":"kocheva2","date":"2016-04-21T08:36:57.898Z","msg":"(No commit Message)","action":"A"}],"scheduler/examples/proc1-c2-rr2.out":[{"revision":78852,"author":"kocheva2","date":"2016-04-21T08:36:57.898Z","msg":"(No commit Message)","action":"A"}],"scheduler/examples/proc1-c2-rr4.out":[{"revision":78852,"author":"kocheva2","date":"2016-04-21T08:36:57.898Z","msg":"(No commit Message)","action":"A"}],"scheduler/examples/proc1.csv":[{"revision":78852,"author":"kocheva2","date":"2016-04-21T08:36:57.898Z","msg":"(No commit Message)","action":"A"}],"scheduler/examples/proc2-c1-fcfs.out":[{"revision":78852,"author":"kocheva2","date":"2016-04-21T08:36:57.898Z","msg":"(No commit Message)","action":"A"}],"scheduler/examples/proc2-c1-pri.out":[{"revision":78852,"author":"kocheva2","date":"2016-04-21T08:36:57.898Z","msg":"(No commit Message)","action":"A"}],"scheduler/examples/proc2-c1-psjf.out":[{"revision":78852,"author":"kocheva2","date":"2016-04-21T08:36:57.898Z","msg":"(No commit Message)","action":"A"}],"scheduler/examples/proc2-c1-rr1.out":[{"revision":78852,"author":"kocheva2","date":"2016-04-21T08:36:57.898Z","msg":"(No commit Message)","action":"A"}],"scheduler/examples/proc2-c1-rr2.out":[{"revision":78852,"author":"kocheva2","date":"2016-04-21T08:36:57.898Z","msg":"(No commit Message)","action":"A"}],"scheduler/examples/proc2-c1-rr4.out":[{"revision":78852,"author":"kocheva2","date":"2016-04-21T08:36:57.898Z","msg":"(No commit Message)","action":"A"}],"scheduler/examples/proc2-c2-fcfs.out":[{"revision":78852,"author":"kocheva2","date":"2016-04-21T08:36:57.898Z","msg":"(No commit Message)","action":"A"}],"scheduler/examples/proc2-c2-pri.out":[{"revision":78852,"author":"kocheva2","date":"2016-04-21T08:36:57.898Z","msg":"(No commit Message)","action":"A"}],"scheduler/examples/proc2-c2-psjf.out":[{"revision":78852,"author":"kocheva2","date":"2016-04-21T08:36:57.898Z","msg":"(No commit Message)","action":"A"}],"scheduler/examples/proc2-c2-rr1.out":[{"revision":78852,"author":"kocheva2","date":"2016-04-21T08:36:57.898Z","msg":"(No commit Message)","action":"A"}],"scheduler/examples/proc2-c2-rr2.out":[{"revision":78852,"author":"kocheva2","date":"2016-04-21T08:36:57.898Z","msg":"(No commit Message)","action":"A"}],"scheduler/examples/proc2-c2-rr4.out":[{"revision":78852,"author":"kocheva2","date":"2016-04-21T08:36:57.898Z","msg":"(No commit Message)","action":"A"}],"scheduler/examples/proc2.csv":[{"revision":78852,"author":"kocheva2","date":"2016-04-21T08:36:57.898Z","msg":"(No commit Message)","action":"A"}],"scheduler/examples/proc3-c1-fcfs.out":[{"revision":78852,"author":"kocheva2","date":"2016-04-21T08:36:57.898Z","msg":"(No commit Message)","action":"A"}],"scheduler/examples/proc3-c1-pri.out":[{"revision":78852,"author":"kocheva2","date":"2016-04-21T08:36:57.898Z","msg":"(No commit Message)","action":"A"}],"scheduler/examples/proc3-c1-psjf.out":[{"revision":78852,"author":"kocheva2","date":"2016-04-21T08:36:57.898Z","msg":"(No commit Message)","action":"A"}],"scheduler/examples/proc3-c1-rr1.out":[{"revision":78852,"author":"kocheva2","date":"2016-04-21T08:36:57.898Z","msg":"(No commit Message)","action":"A"}],"scheduler/examples/proc3-c1-rr2.out":[{"revision":78852,"author":"kocheva2","date":"2016-04-21T08:36:57.898Z","msg":"(No commit Message)","action":"A"}],"scheduler/examples/proc3-c1-rr4.out":[{"revision":78852,"author":"kocheva2","date":"2016-04-21T08:36:57.898Z","msg":"(No commit Message)","action":"A"}],"scheduler/examples/proc3-c2-fcfs.out":[{"revision":78852,"author":"kocheva2","date":"2016-04-21T08:36:57.898Z","msg":"(No commit Message)","action":"A"}],"scheduler/examples/proc3-c2-pri.out":[{"revision":78852,"author":"kocheva2","date":"2016-04-21T08:36:57.898Z","msg":"(No commit Message)","action":"A"}],"scheduler/examples/proc3-c2-psjf.out":[{"revision":78852,"author":"kocheva2","date":"2016-04-21T08:36:57.898Z","msg":"(No commit Message)","action":"A"}],"scheduler/examples/proc3-c2-rr1.out":[{"revision":78852,"author":"kocheva2","date":"2016-04-21T08:36:57.898Z","msg":"(No commit Message)","action":"A"}],"scheduler/examples/proc3-c2-rr2.out":[{"revision":78852,"author":"kocheva2","date":"2016-04-21T08:36:57.898Z","msg":"(No commit Message)","action":"A"}],"scheduler/examples/proc3-c2-rr4.out":[{"revision":78852,"author":"kocheva2","date":"2016-04-21T08:36:57.898Z","msg":"(No commit Message)","action":"A"}],"scheduler/examples/proc3-c4-fcfs.out":[{"revision":78852,"author":"kocheva2","date":"2016-04-21T08:36:57.898Z","msg":"(No commit Message)","action":"A"}],"scheduler/examples/proc3-c4-pri.out":[{"revision":78852,"author":"kocheva2","date":"2016-04-21T08:36:57.898Z","msg":"(No commit Message)","action":"A"}],"scheduler/examples/proc3-c4-psjf.out":[{"revision":78852,"author":"kocheva2","date":"2016-04-21T08:36:57.898Z","msg":"(No commit Message)","action":"A"}],"scheduler/examples/proc3-c4-rr1.out":[{"revision":78852,"author":"kocheva2","date":"2016-04-21T08:36:57.898Z","msg":"(No commit Message)","action":"A"}],"scheduler/examples/proc3-c4-rr2.out":[{"revision":78852,"author":"kocheva2","date":"2016-04-21T08:36:57.898Z","msg":"(No commit Message)","action":"A"}],"scheduler/examples/proc3-c4-rr4.out":[{"revision":78852,"author":"kocheva2","date":"2016-04-21T08:36:57.898Z","msg":"(No commit Message)","action":"A"}],"scheduler/examples/proc3.csv":[{"revision":78852,"author":"kocheva2","date":"2016-04-21T08:36:57.898Z","msg":"(No commit Message)","action":"A"}],"scheduler/examples.pl":[{"revision":78852,"author":"kocheva2","date":"2016-04-21T08:36:57.898Z","msg":"(No commit Message)","action":"A"}],"scheduler/libpriqueue":[{"revision":78852,"author":"kocheva2","date":"2016-04-21T08:36:57.898Z","msg":"(No commit Message)","action":"A"}],"scheduler/libpriqueue/libpriqueue.c":[{"revision":78852,"author":"kocheva2","date":"2016-04-21T08:36:57.898Z","msg":"(No commit Message)","action":"A"}],"scheduler/libpriqueue/libpriqueue.h":[{"revision":78852,"author":"kocheva2","date":"2016-04-21T08:36:57.898Z","msg":"(No commit Message)","action":"A"}],"scheduler/libscheduler":[{"revision":78852,"author":"kocheva2","date":"2016-04-21T08:36:57.898Z","msg":"(No commit Message)","action":"A"}],"scheduler/simulator.c":[{"revision":78852,"author":"kocheva2","date":"2016-04-21T08:36:57.898Z","msg":"(No commit Message)","action":"A"}]},"sizes":{"scheduler/Makefile":2162,"scheduler/examples/proc1-c1-fcfs.out":3763,"scheduler/examples/proc1-c1-pri.out":3762,"scheduler/examples/proc1-c1-psjf.out":3762,"scheduler/examples/proc1-c1-rr1.out":5759,"scheduler/examples/proc1-c1-rr2.out":4678,"scheduler/examples/proc1-c1-rr4.out":4060,"scheduler/examples/proc1-c2-fcfs.out":4154,"scheduler/examples/proc1-c2-pri.out":4153,"scheduler/examples/proc1-c2-psjf.out":4160,"scheduler/examples/proc1-c2-rr1.out":6110,"scheduler/examples/proc1-c2-rr2.out":5035,"scheduler/examples/proc1-c2-rr4.out":4450,"scheduler/examples/proc1.csv":63,"scheduler/examples/proc2-c1-fcfs.out":3611,"scheduler/examples/proc2-c1-pri.out":3580,"scheduler/examples/proc2-c1-psjf.out":3483,"scheduler/examples/proc2-c1-rr1.out":5620,"scheduler/examples/proc2-c1-rr2.out":4485,"scheduler/examples/proc2-c1-rr4.out":3950,"scheduler/examples/proc2-c2-fcfs.out":2791,"scheduler/examples/proc2-c2-pri.out":2790,"scheduler/examples/proc2-c2-psjf.out":3005,"scheduler/examples/proc2-c2-rr1.out":4761,"scheduler/examples/proc2-c2-rr2.out":3628,"scheduler/examples/proc2-c2-rr4.out":3001,"scheduler/examples/proc2.csv":68,"scheduler/examples/proc3-c1-fcfs.out":38161,"scheduler/examples/proc3-c1-pri.out":39542,"scheduler/examples/proc3-c1-psjf.out":35240,"scheduler/examples/proc3-c1-rr1.out":63152,"scheduler/examples/proc3-c1-rr2.out":51370,"scheduler/examples/proc3-c1-rr4.out":44883,"scheduler/examples/proc3-c2-fcfs.out":22448,"scheduler/examples/proc3-c2-pri.out":23414,"scheduler/examples/proc3-c2-psjf.out":22475,"scheduler/examples/proc3-c2-rr1.out":44938,"scheduler/examples/proc3-c2-rr2.out":33913,"scheduler/examples/proc3-c2-rr4.out":27607,"scheduler/examples/proc3-c4-fcfs.out":15389,"scheduler/examples/proc3-c4-pri.out":15205,"scheduler/examples/proc3-c4-psjf.out":15691,"scheduler/examples/proc3-c4-rr1.out":35403,"scheduler/examples/proc3-c4-rr2.out":25101,"scheduler/examples/proc3-c4-rr4.out":19897,"scheduler/examples/proc3.csv":160,"scheduler/examples.pl":394,"scheduler/grade_report.html":13169,"scheduler/libpriqueue/libpriqueue.c":3248,"scheduler/libpriqueue/libpriqueue.h":645,"scheduler/libscheduler/libscheduler.c":9727,"scheduler/libscheduler/libscheduler.h":1698,"scheduler/results.json":11216,"scheduler/simulator.c":13066}}