{"tree":{"text":"Lab15","children":[{"text":"Makefile","icon":"fa fa-file"},{"text":"main.c","icon":"fa fa-file"},{"text":"pi_calc.c","icon":"fa fa-file"},{"text":"pi_calc.h","icon":"fa fa-file"}],"icon":"fa fa-folder"},"commits":{"Lab15":[{"revision":23455,"author":"amahmou2","date":"2015-12-07T08:20:59.155Z","msg":"(No commit Message)","action":"A"}],"Lab15/Makefile":[{"revision":23455,"author":"amahmou2","date":"2015-12-07T08:20:59.155Z","msg":"(No commit Message)","action":"A"}],"Lab15/main.c":[{"revision":23455,"author":"amahmou2","date":"2015-12-07T08:20:59.155Z","msg":"(No commit Message)","action":"A"}],"Lab15/pi_calc.c":[{"revision":23455,"author":"amahmou2","date":"2015-12-07T08:20:59.155Z","msg":"(No commit Message)","action":"A"}],"Lab15/pi_calc.h":[{"revision":23455,"author":"amahmou2","date":"2015-12-07T08:20:59.155Z","msg":"(No commit Message)","action":"A"}]},"sizes":{"Lab15/Makefile":288,"Lab15/main.c":1209,"Lab15/pi_calc.c":1372,"Lab15/pi_calc.h":202}}